Metadata-Version: 1.1
Name: pi-weather-shield
Version: 0.0.2
Summary: Python module to control the TE Connectivity Raspberry Pi Weather Shield
Home-page: https://github.com/TEConnectivity/piweathershield-python
Author: William Markezana
Author-email: william.markezana@te.com
License: MIT License
